napari_opt_handler/__init__.py
napari_opt_handler/_qtwidget.py
napari_opt_handler/_sample_data.py
napari_opt_handler/backtrack.py
napari_opt_handler/corrections.py
napari_opt_handler/napari.yaml
napari_opt_handler/plotting.py
napari_opt_handler/utils.py
napari_opt_handler/widget_settings.py
napari_opt_handler/_tests/__init__.py
napari_opt_handler/_tests/conftest.py
napari_opt_handler/_tests/test_backtrack.py
napari_opt_handler/_tests/test_corr.py
napari_opt_handler/_tests/test_sample_data.py
napari_opt_handler/_tests/test_utils.py
napari_opt_handler/_tests/test_widget.py
napari_opt_handler/_tests/test_widget_qtbot.py
napari_opt_handler/sample_data/16-48-16_0000.tiff
napari_opt_handler/sample_data/16-48-17_0001.tiff
napari_opt_handler/sample_data/16-48-18_0002.tiff
napari_opt_handler/sample_data/16-48-18_0003.tiff
napari_opt_handler/sample_data/16-48-19_0004.tiff
napari_opt_handler/sample_data/16-48-20_0005.tiff
napari_opt_handler/sample_data/16-48-21_0006.tiff
napari_opt_handler/sample_data/corr_hot.tiff
napari_opt_handler/sample_data/dark_field.tiff
napari_opt_handler/sample_data/flat_field.tiff
napari_opt_handler-0.0.3.dist-info/LICENSE
napari_opt_handler-0.0.3.dist-info/METADATA
napari_opt_handler-0.0.3.dist-info/WHEEL
napari_opt_handler-0.0.3.dist-info/entry_points.txt
napari_opt_handler-0.0.3.dist-info/top_level.txt
napari_opt_handler-0.0.3.dist-info/RECORD
