Metadata-Version: 2.1
Name: napari-opt-handler
Version: 0.0.3
Summary: Optical Projection Tomography preprocessing plugin for napari
Author-email: David Palecek <david@stanka.de>, Giorgia Tortora <giorgia.tortora@polimi.it>
License: 
Project-URL: Bug Tracker, https://github.com/QBioImaging/napari-opt-handler/issues
Project-URL: Documentation, https://github.com/QBioImaging/napari-opt-handler#README.md
Project-URL: Source Code, https://github.com/QBioImaging/napari-opt-handler
Project-URL: User Support, https://github.com/QBioImaging/napari-opt-handler/issues
Classifier: Development Status :: 2 - Pre-Alpha
Classifier: Framework :: napari
Classifier: Intended Audience :: Science/Research
Classifier: License :: OSI Approved :: BSD License
Classifier: Operating System :: OS Independent
Classifier: Programming Language :: Python
Classifier: Programming Language :: Python :: 3
Classifier: Programming Language :: Python :: 3 :: Only
Classifier: Programming Language :: Python :: 3.9
Classifier: Programming Language :: Python :: 3.10
Classifier: Programming Language :: Python :: 3.11
Classifier: Programming Language :: Python :: 3.12
Classifier: Topic :: Scientific/Engineering :: Image Processing
Requires-Python: >=3.9
License-File: LICENSE
Requires-Dist: numpy
Requires-Dist: magicgui
Requires-Dist: scikit-image
Requires-Dist: matplotlib
Provides-Extra: napari
Requires-Dist: magicgui ; extra == 'napari'
Requires-Dist: napari[pyqt5] ; extra == 'napari'
Requires-Dist: pooch >=1 ; extra == 'napari'
Requires-Dist: qtpy ; extra == 'napari'
Provides-Extra: testing
Requires-Dist: pre-commit ; extra == 'testing'
Requires-Dist: pytest ; extra == 'testing'
Requires-Dist: pytest-cov ; extra == 'testing'
Requires-Dist: pytest-qt ; extra == 'testing'
Requires-Dist: pytest-mock ; extra == 'testing'
Requires-Dist: pytest-timeout ; extra == 'testing'
Requires-Dist: tox ; extra == 'testing'
